{
  "data": [
    {
      "content": [
  "Hi, I'm Sohaib Mokhliss \ud83d\udc68\u200d\ud83d\udcbb",
  "A passionate software engineer with a focus on backend development, cloud architecture, and DevOps."
      ]
    },
    {
      "content": [
        "I have extensive experience as a full-stack developer, working with modern technologies across web, cloud, and infrastructure.",
        "I enjoy solving complex problems, building scalable systems, and continuously learning new skills."
      ]
    },
    {
      "content": [
        "My interests include cloud computing, distributed systems, automation, and mentoring others in technology.",
        "I'm always open to new challenges and opportunities to collaborate."
      ]
    },
    {
      "content": [
        "Connect with me on <a href=\"https://www.linkedin.com/in/browncj/\" target=\"_blank\" class=\"text-blue\">LinkedIn</a>.",
        "Check out my work on <a href=\"https://github.com/browncj/\" target=\"_blank\" class=\"text-pink\">GitHub</a>."
      ]
    },
    {
      "content": [
        "Use the menu to explore my work, experience, and skills.",
        "Navigate using the arrow keys or Vim motions."
      ]
    }
  ]
}
